vbanimation/__init__.py
vbanimation/__main__.py
vbanimation/align.tex
vbanimation/animation.py
vbanimation/animation_processing.py
vbanimation/audio_processing.py
vbanimation/main.py
vbanimation/other_functions.py
vbanimation/picture/main.aux
vbanimation/picture/main.log
vbanimation/picture/main.pdf
vbanimation/picture/main.png
vbanimation/picture/main.tex
vbanimation/picture/tikz.tex
vbanimation/test_solution.tex
vbanimation/test_solution_without_align.tex
vbanimation/test_tex_processing.py
vbanimation/test_tikzpicture.tex
vbanimation/tex_parsing.py
vbanimation/tex_processing.py
vbanimation-0.1.86.dist-info/METADATA
vbanimation-0.1.86.dist-info/WHEEL
vbanimation-0.1.86.dist-info/entry_points.txt
vbanimation-0.1.86.dist-info/RECORD
