Metadata-Version: 2.1
Name: vbanimation
Version: 0.1.86
Summary: 
Author: vaibhavblayer
Author-email: vaibhavblayer@gmail.com
Requires-Python: >=3.8,<3.13
Classifier: Programming Language :: Python :: 3
Classifier: Programming Language :: Python :: 3.8
Classifier: Programming Language :: Python :: 3.9
Classifier: Programming Language :: Python :: 3.10
Classifier: Programming Language :: Python :: 3.11
Requires-Dist: click (>=8.1.7,<9.0.0)
Requires-Dist: manim (>=0.18.0,<0.19.0)
